Workbook

Sheet Worklog_Tasks&Times
A1: Date | B1: Status | C1: Task | D1: Description/Planning | E1: Task Type | F1: Most suited ILO | G1: Est Hours | H1: Actual Hours | I1: Diff | J1: Task reflection / notes
A2: Week 1
A3: week plan: | B3: - Weekplan item 1 - Weekplan item 2 - Weekplan item 3 - etc
A4: Known Risks | B4: [Enter known possible issues that are a risk for you to finish the high level week planning]
A5: 45901 | B5: Done | C5: Max 4 hours tasks | D5: Meetup with the company supervisor and colleagues in the office | E5: Meeting | F5: A1 | G5: 1 | H5: 1 | I5: =H5-G5 -> 0
A6: 45901 | B6: Done | C6: Max 4 hours tasks | D6: Presentation on introduction to Move Group company | E6: Meeting | F6: A1 | G6: 2 | H6: 2 | I6: =H6-G6 -> 0
A7: 45901 | B7: Done | C7: Max 4 hours tasks | D7: Presentation on how the business operates | E7: Meeting | F7: A1 | G7: 1 | H7: 1 | I7: =H7-G7 -> 0
A8: 45901 | B8: Done | C8: Max 4 hours tasks | D8: Lunch break | E8: Break | F8: - | G8: 1 | H8: 1 | I8: =H8-G8 -> 0
A9: 45901 | B9: Done | C9: Max 4 hours tasks | D9: Presentation on how the business operates | E9: Meeting | F9: A1 | G9: 2 | H9: 2 | I9: =H9-G9 -> 0
A10: 45901 | B10: Done | C10: Max 4 hours tasks | D10: Introduction to Ixolution | E10: Workshop | F10: A1 | G10: 2 | H10: 2 | I10: =H10-G10 -> 0 | J10: Ixolution is the TMS system Move Intremodal uses for their transport management
A11: 45902 | B11: Done | C11: Max 4 hours tasks | D11: Presentation on how the business operates | E11: Meeting | F11: A1 | G11: 2 | H11: 2 | I11: =H11-G11 -> 0
A12: 45902 | B12: Done | C12: Max 4 hours tasks | D12: Follow the introduction course in Move Academy | E12: Workshop | F12: A1 | G12: 2 | H12: 2 | I12: =H12-G12 -> 0
A13: 45902 | B13: Done | C13: Max 4 hours tasks | D13: Lunch break | E13: Break | F13: - | G13: 1 | H13: 1 | I13: =H13-G13 -> 0
A14: 45902 | B14: Done | C14: Max 4 hours tasks | D14: Follow the introduction course in Move Academy | E14: Workshop | F14: A1 | G14: 2 | H14: 2 | I14: =H14-G14 -> 0 | J14: Move Academy - platform for inside education of the Move Group members
A15: 45902 | B15: Done | C15: Max 4 hours tasks | D15: Introduction to Ixolution | E15: Workshop | F15: A1 | G15: 2 | H15: 2 | I15: =H15-G15 -> 0
A16: 45903 | B16: Done | C16: Max 4 hours tasks | D16: Watchin the Introduction course in Move Academy | E16: Study | F16: A1 | G16: 4 | H16: 3 | I16: =H16-G16 -> -1
A17: 45903 | B17: Done | C17: Max 4 hours tasks | D17: Lunch break | E17: Break | F17: - | G17: 1 | H17: 1 | I17: =H17-G17 -> 0
A18: 45903 | B18: Done | C18: Max 4 hours tasks | D18: Learning on the operations in Ixolutions and what data it contains | E18: Workshop | F18: A1 | G18: 2 | H18: 2 | I18: 0
A19: 45904 | B19: Done | C19: Max 4 hours tasks | D19: Watchin the Introduction course in Move Academy | E19: Study | F19: A1 | G19: 2 | H19: 2 | I19: 0
A20: 45904 | B20: Done | C20: Max 4 hours tasks | D20: Introduction to Transpas | E20: Workshop | F20: A1 | G20: 2 | H20: 2 | I20: 0 | J20: Transpas - TMS system that Van Dijk uses for its transport management
A21: 45904 | B21: Done | C21: Max 4 hours tasks | D21: Lunch break | E21: Break | F21: - | G21: 1 | H21: 1 | I21: 0
A22: 45904 | B22: Done | C22: Max 4 hours tasks | D22: Introduction to Transpas and comparison to Ixolution | E22: Workshop | F22: A1 | G22: 3 | H22: 3 | I22: 0
A23: 45905 | B23: Done | C23: Max 4 hours tasks | D23: Watchin the Introduction course in Move Academy | E23: Study | F23: A1 | G23: 3 | H23: 2 | I23: 0
A24: 45905 | B24: Done | C24: Max 4 hours tasks | D24: Introduction to Transpas and comparison to Ixolution | E24: Workshop | F24: A1 | G24: 1 | H24: 1 | I24: 0
A25: 45905 | B25: Done | C25: Max 4 hours tasks | D25: Lunch break | E25: Break | F25: - | G25: 1 | H25: 1 | I25: 0
A26: 45905 | B26: Done | C26: Max 4 hours tasks | D26: Introduction to Transpas and comparison to Ixolution | E26: Workshop | F26: A1 | G26: 3 | H26: 4 | I26: 1
E27: Total Hours | G27: =SUM(G5:G26) -> 41 | H27: =SUM(H5:H26) -> 40 | I27: =H27-G27 -> -1
A28: Week 2
A29: week plan: | B29: - Weekplan item 1 - Weekplan item 2 - Weekplan item 3 - etc
A30: Known Risks | B30: [Enter known possible issues that are a risk for you to finish the high level week planning] - if any
A31: 45908 | B31: Done | C31: Max 4 hours tasks | D31: Introduction to Matillion | E31: Study | F31: B5 | G31: 4 | H31: 4 | I31: =H31-G31 -> 0 | J31: Study on Matillion basics (jobs, transformation, orchestraction)
A32: 45908 | B32: Done | C32: Max 4 hours tasks | D32: Lunch break | E32: Break | F32: - | G32: 1 | H32: 1 | I32: =H32-G32 -> 0
A33: 45908 | B33: Done | C33: Max 4 hours tasks | D33: Snowlfake basics | E33: Study | F33: B5 | G33: 3 | H33: 3 | I33: =H33-G33 -> 0 | J33: Intro to schemas, SQL, queries
A34: 45908 | B34: Done | C34: Max 4 hours tasks | D34: Compare example tables between Transpas and Ixolution | E34: Workshop | F34: B5 | G34: 1 | H34: 1 | I34: =H34-G34 -> 0
A35: 45909 | B35: Done | C35: Max 4 hours tasks | D35: Watchin the Introduction course in Move Academy | E35: Study | F35: A1 | G35: 2 | H35: 2 | I35: =H35-G35 -> 0
A36: 45909 | B36: Done | C36: Max 4 hours tasks | D36: Learn the concept of Incremential loadig in Matillion | E36: Study | F36: B5 | G36: 2 | H36: 2 | I36: =H36-G36 -> 0 | J36: learn about the timestamps, keys, and etc.
A37: 45909 | B37: Done | C37: Max 4 hours tasks | D37: Lunch break | E37: Break | F37: - | G37: 1 | H37: 1 | I37: =H37-G37 -> 0
A38: 45909 | B38: Done | C38: Max 4 hours tasks | D38: Learn the concept of Incremential loadig in Matillion | E38: Study | F38: B5 | G38: 2 | H38: 2 | I38: =H38-G38 -> 0
A39: 45909 | B39: Done | C39: Max 4 hours tasks | D39: Experiment with building a jobs in Matillion | E39: Workshop | F39: B5 | G39: 2 | H39: 2 | I39: =H39-G39 -> 0
A40: 45910 | B40: Done | C40: Max 4 hours tasks | D40: Experiment with building a jobs in Matillion | E40: Workshop | F40: B5 | G40: 2 | H40: 2 | I40: =H40-G40 -> 0
A41: 45910 | B41: Done | C41: Max 4 hours tasks | D41: Explore the business keys and logic behind sats and hubs | E41: Study | F41: B5 | G41: 2 | H41: 2 | I41: =H41-G41 -> 0
A42: 45910 | B42: Done | C42: Max 4 hours tasks | D42: Lunch break | E42: Break | F42: - | G42: 1 | H42: 1 | I42: =H42-G42 -> 0
A43: 45910 | B43: Done | C43: Max 4 hours tasks | D43: Explore the business keys and logic behind sats and hubs | E43: Study | F43: B5 | G43: 2 | H43: 2 | I43: =H43-G43 -> 0
A44: 45910 | B44: Done | C44: Max 4 hours tasks | D44: Create one link and lsat link between two tables | E44: Workshop | F44: B5 | G44: 2 | H44: 2 | I44: =H44-G44 -> 0
A45: 45911 | B45: Done | C45: Max 4 hours tasks | D45: Check the tables in Snowflake | E45: Workshop | F45: B5 | G45: 2 | H45: 2 | I45: =H45-G45 -> 0
A46: 45911 | B46: Done | C46: Max 4 hours tasks | D46: Create links between tables | E46: Workshop | F46: B4 | G46: 2 | H46: 2 | I46: =H46-G46 -> 0
A47: 45911 | B47: Done | C47: Max 4 hours tasks | D47: Lunch break | E47: Break | F47: - | G47: 1 | H47: 1 | I47: =H47-G47 -> 0
A48: 45911 | B48: Done | C48: Max 4 hours tasks | D48: Create a complete view in matilion out of links between tables | E48: Workshop | F48: B4 | G48: 4 | H48: 4 | I48: =H48-G48 -> 0
A49: 45912 | B49: Done | C49: Max 4 hours tasks | D49: Create a complete view in matilion out of links between tables | E49: Workshop | F49: B4 | G49: 2 | H49: 2 | I49: =H49-G49 -> 0
A50: 45912 | B50: Done | C50: Max 4 hours tasks | D50: Check the tables in Snowflake | E50: Workshop | F50: B4 | G50: 2 | H50: 2 | I50: =H50-G50 -> 0 | J50: Check the tables in the database in Snowflake and try to find link between some of them.
A51: 45912 | B51: Done | C51: Max 4 hours tasks | D51: Lunch break | E51: Break | F51: - | G51: 1 | H51: 1 | I51: =H51-G51 -> 0
A52: 45912 | B52: Done | C52: Max 4 hours tasks | D52: Finalize a view in Matillion | E52: Workshop | F52: B4 | G52: 4 | H52: 4 | I52: =H52-G52 -> 0 | J52: The view is made out of connections made between a lot of tables.
E53: Total Hours | G53: =SUM(G29:G52) -> 45 | H53: =SUM(H29:H52) -> 45 | I53: =H53-G53 -> 0
A54: Week 3
A55: week plan: | B55: - Weekplan item 1 - Weekplan item 2 - Weekplan item 3 - etc
A56: Known Risks | B56: [Enter known possible issues that are a risk for you to finish the high level week planning]
A57: 45915 | B57: Done | C57: Max 4 hours tasks | D57: Working on Rit view in Matillion | E57: Workshop | F57: B4 | G57: 2 | H57: 2 | I57: =H57-G57 -> 0
A58: 45915 | B58: Done | C58: Max 4 hours tasks | D58: Exploring the tables in the Database | E58: Workshop | F58: B4 | G58: 2 | H58: 2 | I58: =H58-G58 -> 0
A59: 45915 | B59: Done | C59: Max 4 hours tasks | D59: Lunch break | E59: Break | F59: - | G59: 1 | H59: 1 | I59: =H59-G59 -> 0
A60: 45915 | B60: Done | C60: Max 4 hours tasks | D60: Exploring the tables in the Database | E60: Workshop | F60: B4 | G60: 2 | H60: 1 | I60: =H60-G60 -> -1
A61: 45915 | B61: Done | C61: Max 4 hours tasks | D61: Working on Rit view in Matillion | E61: Workshop | F61: B4 | G61: 1 | H61: 1 | I61: =H61-G61 -> 0
A62: 45916 | B62: Done | C62: Max 4 hours tasks | D62: Explore the KPIs of currecnt Van Dijk reports | E62: Meeting | F62: B4 | G62: 2 | H62: 2 | I62: =H62-G62 -> 0 | J62: Meeting with the director of Van Dijk to explore the current manual reports and the KPIs
A63: 45916 | B63: Done | C63: Max 4 hours tasks | D63: Excellence center IT meeting | E63: Meeting | F63: B9 | G63: 1 | H63: 1 | I63: =H63-G63 -> 0
A64: 45916 | B64: Done | C64: Max 4 hours tasks | D64: Lunch break | E64: Break | F64: - | G64: 1 | H64: 1 | I64: =H64-G64 -> 0
A65: 45916 | B65: Done | C65: Max 4 hours tasks | D65: Explore the KPIs of currecnt Van Dijk reports | E65: Meeting | F65: B4 | G65: 2 | H65: 2 | I65: =H65-G65 -> 0
A66: 45916 | B66: Done | C66: Max 4 hours tasks | D66: Exploring the tables in the Database | E66: Workshop | F66: B4 | G66: 2 | H66: 2 | I66: =H66-G66 -> 0
A67: 45917 | B67: Done | C67: Max 4 hours tasks | D67: Creating links between tables | E67: Workshop | F67: B5 | G67: 4 | H67: 3 | I67: =H67-G67 -> -1 | J67: Check the tables in the database in Snowflake and link the relevant ones
A68: 45917 | B68: Done | C68: Max 4 hours tasks | D68: Lunch break | E68: Break | F68: - | G68: 1 | H68: 1 | I68: =H68-G68 -> 0
A69: 45917 | B69: Done | C69: Max 4 hours tasks | D69: Sit next to a truck planner | E69: Workshop | F69: B4 | G69: 2 | H69: 2 | I69: =H69-G69 -> 0 | J69: I sat with a truck planner to see how the process of receiving an order to finalizing it is done and what data they use in
A70: 45917 | B70: Done | C70: Max 4 hours tasks | D70: Creating links between tables | E70: Workshop | F70: B5 | G70: 2 | H70: 2 | I70: =H70-G70 -> 0
A71: 45918 | B71: Done | C71: Max 4 hours tasks | D71: Exploring the tables in the Database | E71: Workshop | F71: B4 | G71: 2 | H71: 2 | I71: =H71-G71 -> 0 | J71: Check the tables in the database in Snowflake and find a relation between them
A72: 45918 | B72: Done | C72: Max 4 hours tasks | D72: Creating links between tables | E72: Workshop | F72: B5 | G72: 2 | H72: 2 | I72: =H72-G72 -> 0 | J72: Linking some of the relevant tables using LNK and LSAT LNK links
A73: 45918 | B73: Done | C73: Max 4 hours tasks | D73: Lunch break | E73: Break | F73: - | G73: 1 | H73: 1 | I73: =H73-G73 -> 0
A74: 45918 | B74: Done | C74: Max 4 hours tasks | D74: Half-day with a truck driver | E74: Workshop | F74: B4 | G74: 4 | H74: 4 | I74: =H74-G74 -> 0 | J74: went on a half-day with a truck driver to deliver/pick some orders to see the process from the other side
A75: 45919 | B75: Done | C75: Max 4 hours tasks | D75: Exploring the tables in the Database | E75: Workshop | F75: B4 | G75: 4 | H75: 3 | I75: =H75-G75 -> -1 | J75: Check the tables in the database in Snowflake and find a relation between them
A76: 45919 | B76: Done | C76: Max 4 hours tasks | D76: Lunch break | E76: Break | F76: - | G76: 1 | H76: 1 | I76: =H76-G76 -> 0
A77: 45919 | B77: Done | C77: Max 4 hours tasks | D77: Finalize the first complete view in Matillion | E77: Workshop | F77: B5 | G77: 4 | H77: 4 | I77: =H77-G77 -> 0 | J77: Finalized the first view related to the Rits (Transport Actions) in Matillion
E78: Total Hours | G78: =SUM(G57:G77) -> 43 | H78: =SUM(H57:H77) -> 40 | I78: =H78-G78 -> -3
A79: Week 4
A80: week plan: | B80: - Weekplan item 1 - Weekplan item 2 - Weekplan item 3 - etc
A81: Known Risks | B81: [Enter known possible issues that are a risk for you to finish the high level week planning]
A82: 45922 | B82: Done | C82: Max 4 hours tasks | D82: Working on Linking the tables in Matillion | E82: Workshop | F82: B5 | G82: 2 | H82: 2 | I82: =H82-G82 -> 0
A83: 45922 | B83: Done | C83: Max 4 hours tasks | D83: Exploring the tables in the Snowflake | E83: Workshop | F83: B4 | G83: 2 | H83: 2 | I83: =H83-G83 -> 0
A84: 45922 | B84: Done | C84: Max 4 hours tasks | D84: Lunch break | E84: Break | F84: - | G84: 1 | H84: 1 | I84: =H84-G84 -> 0
A85: 45922 | B85: Done | C85: Max 4 hours tasks | D85: Make a plan for the whole duration of the placement | E85: Planning | F85: B9 | G85: 2 | H85: 2 | I85: =H85-G85 -> 0 | J85: Made a comprehensive plan for the whole duration of the internship divided into 5 phases
A86: 45922 | B86: Done | C86: Max 4 hours tasks | D86: Continue working on the tables in Matillion | E86: Workshop | F86: B5 | G86: 2 | H86: 2 | I86: =H86-G86 -> 0
A87: 45923 | B87: Done | C87: Max 4 hours tasks | D87: Weekly update meeting with Tomas | E87: Meeting | F87: B9 | G87: 1 | H87: 1 | I87: =H87-G87 -> 0 | J87: Weekly meeting with supervisor to update him what have been done during the week and if we are stick to schedule
A88: 45923 | B88: Done | C88: Max 4 hours tasks | D88: Working on the tables in Matillion | E88: Workshop | F88: B5 | G88: 1 | H88: 1 | I88: =H88-G88 -> 0
A89: 45923 | B89: Done | C89: Max 4 hours tasks | D89: Excellence center IT meeting | E89: Meeting | F89: B9 | G89: 1 | H89: 1 | I89: =H89-G89 -> 0
A90: 45923 | B90: Done | C90: Max 4 hours tasks | D90: Lunch break | E90: Break | F90: - | G90: 1 | H90: 1 | I90: =H90-G90 -> 0
A91: 45923 | B91: Done | C91: Max 4 hours tasks | D91: Working on links to Vracht table | E91: Workshop | F91: B5 | G91: 4 | H91: 3 | I91: =H91-G91 -> -1 | J91: Vracht table is the largest in the database and contains more than 100 columns
A92: 45924 | B92: Done | C92: Max 4 hours tasks | D92: Working on links to Vracht table | E92: Workshop | F92: B5 | G92: 3 | H92: 3 | I92: =H92-G92 -> 0
A93: 45924 | B93: Done | C93: Max 4 hours tasks | D93: Lunch break | E93: Break | F93: - | G93: 1 | H93: 1 | I93: =H93-G93 -> 0
A94: 45924 | B94: Done | C94: Max 4 hours tasks | D94: Meeting with Sven about the planning | E94: Meeting | F94: B9 | G94: 1 | H94: 1 | I94: =H94-G94 -> 0 | J94: Went on a meeting with Sven to discuss the planning and make adjustments where needed
A95: 45924 | B95: Done | C95: Max 4 hours tasks | D95: Working on links to Vracht table | E95: Workshop | F95: B5 | G95: 3 | H95: 2 | I95: =H95-G95 -> -1
A96: 45925 | B96: Done | C96: Max 4 hours tasks | D96: Exploring the tables in the Snowflake related to Vracht one | E96: Workshop | F96: B4 | G96: 2 | H96: 2 | I96: =H96-G96 -> 0
A97: 45925 | B97: Done | C97: Max 4 hours tasks | D97: Working on links to Vracht table | E97: Workshop | F97: B5 | G97: 2 | H97: 2 | I97: =H97-G97 -> 0
A98: 45925 | B98: Done | C98: Max 4 hours tasks | D98: Lunch break | E98: Break | F98: - | G98: 1 | H98: 1 | I98: =H98-G98 -> 0
A99: 45925 | B99: Done | C99: Max 4 hours tasks | D99: Meeting with Sven about the Vracht table | E99: Meeting | F99: B9 | G99: 1 | H99: 1 | I99: =H99-G99 -> 0 | J99: Discussed the issues with Vracht table because it contained data only for a couple of months ago
A100: 45925 | B100: Done | C100: Max 4 hours tasks | D100: Finalize the Vracht view | E100: Workshop | F100: B5 | G100: 2 | H100: 2 | I100: =H100-G100 -> 0 | J100: Made small tables linking to vracht
...

Sheet Overview
B2: Learning Objective | C2: W1 | D2: W2 | E2: W3 | F2: W4 | G2: W5 | H2: W6 | I2: W7 | J2: W8 | K2: Total Hours for objective
B3: ='Drop-downs'!C2 -> - | K3: =SUM(C3:J3) -> 0
B4: ='Drop-downs'!C3 -> A1 | C4: =IFERROR(__xludf.DUMMYFUNCTION("IFERROR(SUM(FILTER('Worklog_Tasks&Times'!$H$5:$H$14,'Worklog_Tasks&Times'!$F$5:$F$14=$B4)),0)"),0) -> 0 | K4: =SUM(C4:J4) -> 0
B5: ='Drop-downs'!C4 -> A2 | K5: =SUM(C5:J5) -> 0
B6: ='Drop-downs'!C5 -> A3 | K6: =SUM(C6:J6) -> 0
B7: ='Drop-downs'!C6 -> B4 | K7: =SUM(C7:J7) -> 0
B8: ='Drop-downs'!C7 -> B5 | K8: =SUM(C8:J8) -> 0
B9: ='Drop-downs'!C8 -> B6 | K9: =SUM(C9:J9) -> 0
B10: ='Drop-downs'!C9 -> C7 | K10: =SUM(C10:J10) -> 0
B11: ='Drop-downs'!C10 -> C8 | K11: =SUM(C11:J11) -> 0
B12: TOTAL HOURS PER WEEK | C12: =SUM(C3:C11) -> 0 | D12: =SUM(D3:D11) -> 0 | E12: =SUM(E3:E11) -> 0 | F12: =SUM(F3:F11) -> 0 | G12: =SUM(G3:G11) -> 0 | H12: =SUM(H3:H11) -> 0 | I12: =SUM(I3:I11) -> 0 | J12: =SUM(J3:J11) -> 0
B14: Use this to plan a high level allocation for all 320 hours you are expected to devote to the course during this block. How do you want to allocate your hours for each week? Why 320 hours? The European Higher Education Framework states that an academic credit is expected to require 25-28 hours to earn. You earn 15 credits per block, so you should be expected to devote 375 hours to accomplish that. CMGT students do fewer hours because the program is more intense.
B18: Use a formula like this to get your data from Worklog sheet : =IFERROR(SUM(FILTER('Worklog_Tasks&Times'!$H$5:$H$14,'Worklog_Tasks&Times'!$F$5:$F$14=$B4)),0)

Sheet Drop-downs
A1: Task Status | B1: Task Type | C1: ILO selection
A2: - | B2: - | C2: -
A3: Planned | B3: Design | C3: A1
A4: Unplanned | B4: Meeting | C4: A2
A5: Blocked | B5: Programming | C5: A3
A6: In-Progress | B6: Research | C6: B4
A7: Done | B7: Testing | C7: B5
A8: Delayed | B8: Workshop | C8: B6
A9: Cancelled | B9: Planning | C9: C7
B10: Evidencing | C10: C8
B11: Debugging | C11: C9
B12: Lecture
B13: Study
B14: Unplanned
B15: Distraction
B16: Break
